librelingo_yaml_loader/__init__.py
librelingo_yaml_loader/_spelling.py
librelingo_yaml_loader/module.json
librelingo_yaml_loader/skill.json
librelingo_yaml_loader/yaml_loader.py
librelingo_yaml_loader-1.12.0.dist-info/METADATA
librelingo_yaml_loader-1.12.0.dist-info/WHEEL
librelingo_yaml_loader-1.12.0.dist-info/RECORD
